angrop/__init__.py
angrop/arch.py
angrop/common.py
angrop/errors.py
angrop/rop.py
angrop/rop_block.py
angrop/rop_chain.py
angrop/rop_gadget.py
angrop/rop_utils.py
angrop/rop_value.py
angrop/chain_builder/__init__.py
angrop/chain_builder/builder.py
angrop/chain_builder/func_caller.py
angrop/chain_builder/mem_changer.py
angrop/chain_builder/mem_writer.py
angrop/chain_builder/pivot.py
angrop/chain_builder/reg_mover.py
angrop/chain_builder/reg_setter.py
angrop/chain_builder/shifter.py
angrop/chain_builder/sys_caller.py
angrop/gadget_finder/__init__.py
angrop/gadget_finder/gadget_analyzer.py
angrop-9.2.12.post3.dist-info/licenses/LICENSE
angrop-9.2.12.post3.dist-info/METADATA
angrop-9.2.12.post3.dist-info/WHEEL
angrop-9.2.12.post3.dist-info/top_level.txt
angrop-9.2.12.post3.dist-info/RECORD
