Metadata-Version: 2.4
Name: angrop
Version: 9.2.12.post3
Summary: The rop chain builder based off of angr
Home-page: https://github.com/angr/angrop
License: BSD 2 Clause
Classifier: License :: OSI Approved :: BSD License
Classifier: Programming Language :: Python :: 3
Classifier: Programming Language :: Python :: 3.6
Requires-Python: >=3.6
License-File: LICENSE
Requires-Dist: angr
Requires-Dist: tqdm
Dynamic: license-file
